{
  "player_pos": [13.5, 17],
  "ghosts_pos": [[11.5,26],	[13.5,26],	[15.5,26],	[13.5,23]],
  "fruit_pos" : [13.5,11],
  "big_dots_pos" : [[1,1],[1,23],[26,1],[26,23]],
  "not_dots_rect" : [[7,21,20,30],[0,29,6,29],[21,29,27,29]],
  "slow_ghost_rect" : [[0,29,3,29],[24,29,27,29]],
  "cant_up_ghost_rect": [[0,0,0,0]],
  "map":[
    [[2],	[1],	[1],	[1],	[1],	[1],	[1],	[1],	[1],	[1],	[1],	[1],	[1],	[1],	[1],	[1],	[1],	[1],	[1],	[1],	[1],	[1],	[1],	[1],	[1],	[1],	[1],	[2,1]],
    [[1,3],	[0],	[0],	[0],	[0],	[0],	[0],	[0],	[0],	[0],	[0],	[0],	[0],	[0],	[0],	[0],	[0],	[0],	[0],	[0],	[0],	[0],	[0],	[0],	[0],	[0],	[0],	[1,1]],
    [[1,3],	[0],	[5],	[4,2],	[4,2],	[5,1],	[0],	[5],	[4,2],	[4,2],	[5,1],	[0],	[5],	[4,2],	[4,2],	[5,1],	[0],	[5],	[4,2],	[4,2],	[4,2],	[4,2],	[4,2],	[4,2],	[4,2],	[5,1],	[0],	[1,1]],
    [[1,3],	[0],	[4,1],	[0],	[0],	[4,3],	[0],	[4,1],	[0],	[0],	[4,3],	[0],	[4,1],	[0],	[0],	[4,3],	[0],	[4,1],	[0],	[0],	[0],	[0],	[0],	[0],	[0],	[4,3],	[0],	[1,1]],
    [[1,3],	[0],	[4,1],	[0],	[0],	[4,3],	[0],	[4,1],	[0],	[0],	[4,3],	[0],	[4,1],	[0],	[0],	[4,3],	[0],	[4,1],	[0],	[0],	[0],	[0],	[0],	[0],	[0],	[4,3],	[0],	[1,1]],
    [[1,3],	[0],	[5,3],	[1],	[1],	[5,2],	[0],	[5,3],	[1],	[1],	[5,2],	[0],	[5,3],	[1],	[1],	[5,2],	[0],	[5,3],	[1],	[1],	[1],	[1],	[1],	[1],	[1],	[5,2],	[0],	[1,1]],
    [[1,3],	[0],	[0],	[0],	[0],	[0],	[0],	[0],	[0],	[0],	[0],	[0],	[0],	[0],	[0],	[0],	[0],	[0],	[0],	[0],	[0],	[0],	[0],	[0],	[0],	[0],	[0],	[1,1]],
    [[1,3],	[0],	[5],	[4,2],	[4,2],	[4,2],	[4,2],	[4,2],	[4,2],	[4,2],	[4,2],	[4,2],	[4,2],	[4,2],	[4,2],	[5,1],	[0],	[5],	[4,2],	[4,2],	[5,1],	[0],	[5],	[4,2],	[4,2],	[5,1],	[0],	[1,1]],
    [[1,3],	[0],	[4,1],	[0],	[0],	[0],	[0],	[0],	[0],	[0],	[0],	[0],	[0],	[0],	[0],	[4,3],	[0],	[4,1],	[0],	[0],	[4,3],	[0],	[4,1],	[0],	[0],	[4,3],	[0],	[1,1]],
    [[1,3],	[0],	[4,1],	[0],	[0],	[0],	[0],	[0],	[0],	[0],	[0],	[0],	[0],	[0],	[0],	[4,3],	[0],	[4,1],	[0],	[0],	[4,3],	[0],	[4,1],	[0],	[0],	[4,3],	[0],	[1,1]],
    [[1,3],	[0],	[5,3],	[1],	[1],	[1],	[1],	[1],	[1],	[1],	[1],	[1],	[1],	[1],	[1],	[5,2],	[0],	[5,3],	[1],	[1],	[5,2],	[0],	[5,3],	[1],	[1],	[5,2],	[0],	[1,1]],
    [[1,3],	[0],	[0],	[0],	[0],	[0],	[0],	[0],	[0],	[0],	[0],	[0],	[0],	[0],	[0],	[0],	[0],	[0],	[0],	[0],	[0],	[0],	[0],	[0],	[0],	[0],	[0],	[1,1]],
    [[3,7],	[4,2],	[4,2],	[5,1],	[0],	[5],	[4,2],	[4,2],	[4,2],	[4,2],	[4,2],	[4,2],	[4,2],	[4,2],	[4,2],	[4,2],	[4,2],	[4,2],	[4,2],	[4,2],	[4,2],	[4,2],	[5,1],	[0],	[5],	[4,2],	[4,2],	[3,1]],
    [[3,3],	[4],	[4],	[5,2],	[0],	[5,3],	[4],	[4],	[4],	[4],	[4],	[4],	[4],	[5,1],	[5],	[4],	[4],	[4],	[4],	[4],	[4],	[4],	[5,2],	[0],	[5,3],	[4],	[4],	[3,5]],
    [[1,3],	[0],	[0],	[0],	[0],	[0],	[0],	[0],	[0],	[0],	[0],	[0],	[0],	[4,1],	[4,3],	[0],	[0],	[0],	[0],	[0],	[0],	[0],	[0],	[0],	[0],	[0],	[0],	[1,1]],
    [[1,3],	[0],	[5],	[4,2],	[4,2],	[5,1],	[0],	[5],	[4,2],	[4,2],	[4,2],	[5,1],	[0],	[4,1],	[4,3],	[0],	[5],	[4,2],	[4,2],	[4,2],	[5,1],	[0],	[5],	[4,2],	[4,2],	[5,1],	[0],	[1,1]],
    [[1,3],	[0],	[5,3],	[4],	[4],	[5,2],	[0],	[5,3],	[4],	[4],	[5,1],	[4,3],	[0],	[5,3],	[5,2],	[0],	[4,1],	[5],	[4],	[4],	[5,2],	[0],	[5,3],	[4],	[4],	[5,2],	[0],	[1,1]],
    [[1,3],	[0],	[0],	[0],	[0],	[0],	[0],	[0],	[0],	[0],	[4,1],	[4,3],	[0],	[0],	[0],	[0],	[4,1],	[4,3],	[0],	[0],	[0],	[0],	[0],	[0],	[0],	[0],	[0],	[1,1]],
    [[3,7],	[4,2],	[4,2],	[5,1],	[0],	[5],	[4,2],	[4,2],	[5,1],	[0],	[4,1],	[4,3],	[0],	[5],	[5,1],	[0],	[4,1],	[4,3],	[0],	[5],	[4,2],	[4,2],	[5,1],	[0],	[5],	[4,2],	[4,2],	[3,1]],
    [[3,3],	[4],	[4],	[5,2],	[0],	[5,3],	[4],	[5,1],	[4,3],	[0],	[5,3],	[5,2],	[0],	[4,1],	[4,3],	[0],	[5,3],	[5,2],	[0],	[4,1],	[5],	[4],	[5,2],	[0],	[5,3],	[4],	[4],	[3,5]],
    [[1,3],	[0],	[0],	[0],	[0],	[0],	[0],	[4,1],	[4,3],	[0],	[0],	[0],	[0],	[4,1],	[4,3],	[0],	[0],	[0],	[0],	[4,1],	[4,3],	[0],	[0],	[0],	[0],	[0],	[0],	[1,1]],
    [[1,3],	[0],	[5],	[4,2],	[4,2],	[5,1],	[0],	[4,1],	[4,3],	[0],	[5],	[4,2],	[4,2],	[5,2],	[5,3],	[4,2],	[4,2],	[5,1],	[0],	[4,1],	[4,3],	[0],	[5],	[4,2],	[4,2],	[5,1],	[0],	[1,1]],
    [[1,3],	[0],	[5,3],	[4],	[5,1],	[4,3],	[0],	[5,3],	[5,2],	[0],	[5,3],	[4],	[4],	[4],	[4],	[4],	[4],	[5,2],	[0],	[5,3],	[5,2],	[0],	[4,1],	[5],	[4],	[5,2],	[0],	[1,1]],
    [[1,3],	[0],	[0],	[0],	[4,1],	[4,3],	[0],	[0],	[0],	[0],	[0],	[0],	[0],	[0],	[0],	[0],	[0],	[0],	[0],	[0],	[0],	[0],	[4,1],	[4,3],	[0],	[0],	[0],	[1,1]],
    [[2,3],	[1,2],	[5,1],	[0],	[4,1],	[4,3],	[0],	[5],	[5,1],	[0],	[6],	[1,2],	[8],	[7],	[7],	[8,4],	[1,2],	[6,1],	[0],	[5],	[5,1],	[0],	[4,1],	[4,3],	[0],	[5],	[1,2],	[2,2]],
    [[0],	[0],	[1,3],	[0],	[5,3],	[5,2],	[0],	[4,1],	[4,3],	[0],	[1,1],	[0],	[0],	[0],	[0],	[0],	[0],	[1,3],	[0],	[4,1],	[4,3],	[0],	[5,3],	[5,2],	[0],	[1,1],	[0],	[0]],
    [[0],	[0],	[1,3],	[0],	[0],	[0],	[0],	[4,1],	[4,3],	[0],	[1,1],	[0],	[0],	[0],	[0],	[0],	[0],	[1,3],	[0],	[4,1],	[4,3],	[0],	[0],	[0],	[0],	[1,1],	[0],	[0]],
    [[0],	[0],	[1,3],	[0],	[5],	[4,2],	[4,2],	[5,2],	[4,3],	[0],	[1,1],	[0],	[0],	[0],	[0],	[0],	[0],	[1,3],	[0],	[4,1],	[5,3],	[4,2],	[4,2],	[5,1],	[0],	[1,1],	[0],	[0]],
    [[1],	[1],	[5,2],	[0],	[5,3],	[4],	[4],	[4],	[5,2],	[0],	[6,3],	[1],	[1],	[1],	[1],	[1],	[1],	[6,2],	[0],	[5,3],	[4],	[4],	[4],	[5,2],	[0],	[5,3],	[1],	[1]],
    [[0],	[0],	[0],	[0],	[0],	[0],	[0],	[0],	[0],	[0],	[0],	[0],	[0],	[0],	[0],	[0],	[0],	[0],	[0],	[0],	[0],	[0],	[0],	[0],	[0],	[0],	[0],	[0]],
    [[1,2],	[1,2],	[1,2],	[1,2],	[1,2],	[1,2],	[1,2],	[1,2],	[1,2],	[1,2],	[1,2],	[1,2],	[1,2],	[1,2],	[1,2],	[1,2],	[1,2],	[1,2],	[1,2],	[1,2],	[1,2],	[1,2],	[1,2],	[1,2],	[1,2],	[1,2],	[1,2],	[1,2]]
  ],
  "collision_map": [
    [0,	0,	0,	0,	0,	0,	0,	0,	0,	0,	0,	0,	0,	0,	0,	0,	0,	0,	0,	0,	0,	0,	0,	0,	0,	0,	0,	0],
    [0,	3,	5,	5,	5,	5,	7,	5,	5,	5,	5,	7,	5,	5,	5,	5,	7,	5,	5,	5,	5,	5,	5,	5,	5,	5,	6,	0],
    [0,	10,	0,	0,	0,	0,	10,	0,	0,	0,	0,	10,	0,	0,	0,	0,	10,	0,	0,	0,	0,	0,	0,	0,	0,	0,	10,	0],
    [0,	10,	0,	0,	0,	0,	10,	0,	0,	0,	0,	10,	0,	0,	0,	0,	10,	0,	0,	0,	0,	0,	0,	0,	0,	0,	10,	0],
    [0,	10,	0,	0,	0,	0,	10,	0,	0,	0,	0,	10,	0,	0,	0,	0,	10,	0,	0,	0,	0,	0,	0,	0,	0,	0,	10,	0],
    [0,	10,	0,	0,	0,	0,	10,	0,	0,	0,	0,	10,	0,	0,	0,	0,	10,	0,	0,	0,	0,	0,	0,	0,	0,	0,	10,	0],
    [0,	11,	5,	5,	5,	5,	13,	5,	5,	5,	5,	13,	5,	5,	5,	5,	15,	5,	5,	5,	5,	7,	5,	5,	5,	5,	14,	0],
    [0,	10,	0,	0,	0,	0,	0,	0,	0,	0,	0,	0,	0,	0,	0,	0,	10,	0,	0,	0,	0,	10,	0,	0,	0,	0,	10,	0],
    [0,	10,	0,	0,	0,	0,	0,	0,	0,	0,	0,	0,	0,	0,	0,	0,	10,	0,	0,	0,	0,	10,	0,	0,	0,	0,	10,	0],
    [0,	10,	0,	0,	0,	0,	0,	0,	0,	0,	0,	0,	0,	0,	0,	0,	10,	0,	0,	0,	0,	10,	0,	0,	0,	0,	10,	0],
    [0,	10,	0,	0,	0,	0,	0,	0,	0,	0,	0,	0,	0,	0,	0,	0,	10,	0,	0,	0,	0,	10,	0,	0,	0,	0,	10,	0],
    [0,	9,	5,	5,	7,	5,	5,	5,	5,	5,	5,	5,	5,	5,	5,	5,	13,	5,	5,	5,	5,	13,	5,	7,	5,	5,	12,	0],
    [0,	0,	0,	0,	10,	0,	0,	0,	0,	0,	0,	0,	0,	0,	0,	0,	0,	0,	0,	0,	0,	0,	0,	10,	0,	0,	0,	0],
    [0,	0,	0,	0,	10,	0,	0,	0,	0,	0,	0,	0,	0,	0,	0,	0,	0,	0,	0,	0,	0,	0,	0,	10,	0,	0,	0,	0],
    [0,	3,	5,	5,	13,	5,	7,	5,	5,	5,	5,	5,	6,	0,	0,	3,	5,	5,	5,	5,	5,	7,	5,	13,	5,	5,	6,	0],
    [0,	10,	0,	0,	0,	0,	10,	0,	0,	0,	0,	0,	10,	0,	0,	10,	0,	0,	0,	0,	0,	10,	0,	0,	0,	0,	10,	0],
    [0,	10,	0,	0,	0,	0,	10,	0,	0,	0,	0,	0,	10,	0,	0,	10,	0,	0,	0,	0,	0,	10,	0,	0,	0,	0,	10,	0],
    [0,	9,	5,	5,	7,	5,	13,	5,	5,	6,	0,	0,	11,	5,	5,	14,	0,	0,	3,	5,	5,	13,	5,	7,	5,	5,	12,	0],
    [0,	0,	0,	0,	10,	0,	0,	0,	0,	10,	0,	0,	10,	0,	0,	10,	0,	0,	10,	0,	0,	0,	0,	10,	0,	0,	0,	0],
    [0,	0,	0,	0,	10,	0,	0,	0,	0,	10,	0,	0,	10,	0,	0,	10,	0,	0,	10,	0,	0,	0,	0,	10,	0,	0,	0,	0],
    [0,	3,	5,	5,	13,	5,	6,	0,	0,	11,	5,	5,	12,	0,	0,	9,	5,	5,	14,	0,	0,	3,	5,	13,	5,	5,	6,	0],
    [0,	10,	0,	0,	0,	0,	10,	0,	0,	10,	0,	0,	0,	0,	0,	0,	0,	0,	10,	0,	0,	10,	0,	0,	0,	0,	10,	0],
    [0,	10,	0,	0,	0,	0,	10,	0,	0,	10,	0,	0,	0,	0,	0,	0,	0,	0,	10,	0,	0,	10,	0,	0,	0,	0,	10,	0],
    [0,	9,	5,	6,	0,	0,	11,	5,	5,	15,	5,	5,	5,	5,	5,	5,	5,	5,	15,	5,	5,	14,	0,	0,	3,	5,	12,	0],
    [0,	0,	0,	10,	0,	0,	10,	0,	0,	10,	0,	0,	0,	0,	0,	0,	0,	0,	10,	0,	0,	10,	0,	0,	10,	0,	0,	0],
    [0,	0,	0,	10,	0,	0,	10,	0,	0,	10,	0,	0,	0,	0,	0,	0,	0,	0,	10,	0,	0,	10,	0,	0,	10,	0,	0,	0],
    [0,	0,	0,	11,	5,	5,	12,	0,	0,	10,	0,	0,	0,	0,	0,	0,	0,	0,	10,	0,	0,	9,	5,	5,	14,	0,	0,	0],
    [0,	0,	0,	10,	0,	0,	0,	0,	0,	10,	0,	0,	0,	0,	0,	0,	0,	0,	10,	0,	0,	0,	0,	0,	10,	0,	0,	0],
    [0,	0,	0,	10,	0,	0,	0,	0,	0,	10,	0,	0,	0,	0,	0,	0,	0,	0,	10,	0,	0,	0,	0,	0,	10,	0,	0,	0],
    [5,	5,	5,	13,	5,	5,	5,	5,	5,	13,	5,	5,	5,	5,	5,	5,	5,	5,	13,	5,	5,	5,	5,	5,	13,	5,	5,	5],
    [0,	0,	0,	0,	0,	0,	0,	0,	0,	0,	0,	0,	0,	0,	0,	0,	0,	0,	0,	0,	0,	0,	0,	0,	0,	0,	0,	0]

  ]
}
